prpc/application.py
prpc/client.py
prpc/server.py
prpc/service.py
prpc/protocol/base.py
prpc/protocol/msgpack.py
prpc-0.0.1.dev32.dist-info/DESCRIPTION.rst
prpc-0.0.1.dev32.dist-info/METADATA
prpc-0.0.1.dev32.dist-info/RECORD
prpc-0.0.1.dev32.dist-info/WHEEL
prpc-0.0.1.dev32.dist-info/metadata.json
prpc-0.0.1.dev32.dist-info/pbr.json
prpc-0.0.1.dev32.dist-info/top_level.txt
