Metadata-Version: 2.0
Name: prpc
Version: 0.0.1.dev32
Summary: buh rpc
Home-page: http://prpc.readthedocs.io/
Author: Zack Buhman
Author-email: zack@buhman.org
License: UNKNOWN
Platform: UNKNOWN
Classifier: Development Status :: 5 - Production/Stable
Classifier: Intended Audience :: Developers
Classifier: License :: OSI Approved :: GNU Affero General Public License v3 or later (AGPLv3+)
Classifier: Operating System :: POSIX :: Linux
Classifier: Programming Language :: Python
Classifier: Programming Language :: Python :: 3 :: Only
Classifier: Programming Language :: Python :: 3.5
Classifier: Programming Language :: Python :: 3.6
Requires-Dist: attrs (>=16.3.0)
Requires-Dist: msgpack-ext (>=0.1.2)
Requires-Dist: structlog (>=17.2.0)
Requires-Dist: trio (~=0.1.0)
